rkivacc/__init__.py
rkivacc/report.py
rkivacc-1.0.0.dist-info/LICENSE.txt
rkivacc-1.0.0.dist-info/METADATA
rkivacc-1.0.0.dist-info/WHEEL
rkivacc-1.0.0.dist-info/top_level.txt
rkivacc-1.0.0.dist-info/RECORD
