Metadata-Version: 2.1
Name: rkivacc
Version: 1.0.0
Summary: A simple python library for pulling vaccination data from the RKI
Home-page: https://github.com/spycrab/rkivacc
Author: spycrab0
Author-email: spycrab@users.noreply.github.com
License: UNKNOWN
Platform: UNKNOWN
Classifier: Programming Language :: Python :: 3
Classifier: License :: OSI Approved :: MIT License
Classifier: Operating System :: OS Independent
Requires-Python: >=3.6
Requires-Dist: requests
Requires-Dist: openpyxl
